[
  { "x": 0.00, "msl": 9.70 },
  { "x": 1.06, "msl": 9.71 },
  { "x": 2.12, "msl": 9.74 },
  { "x": 3.18, "msl": 9.10 },
  { "x": 4.24, "msl": 8.44 },
  { "x": 5.30, "msl": 7.63 },
  { "x": 6.36, "msl": 6.96 },
  { "x": 7.42, "msl": 6.31 },
  { "x": 8.48, "msl": 5.56 },
  { "x": 9.54, "msl": 4.98 },
  { "x": 10.60, "msl": 4.45 },
  { "x": 11.66, "msl": 3.90 },
  { "x": 12.72, "msl": 3.53 },
  { "x": 13.78, "msl": 3.24 },
  { "x": 14.84, "msl": 3.05 },
  { "x": 15.90, "msl": 2.88 },
  { "x": 16.96, "msl": 2.77 },
  { "x": 18.02, "msl": 2.69 },
  { "x": 19.08, "msl": 2.62 },
  { "x": 20.14, "msl": 2.56 },
  { "x": 21.20, "msl": 2.52 },
  { "x": 22.26, "msl": 2.47 },
  { "x": 23.32, "msl": 2.44 },
  { "x": 24.38, "msl": 2.42 },
  { "x": 25.44, "msl": 2.41 },
  { "x": 26.50, "msl": 2.40 },
  { "x": 27.56, "msl": 2.42 },
  { "x": 28.62, "msl": 2.44 },
  { "x": 29.68, "msl": 2.45 },
  { "x": 30.74, "msl": 2.51 },
  { "x": 31.80, "msl": 2.60 },
  { "x": 32.86, "msl": 2.67 },
  { "x": 33.92, "msl": 2.77 },
  { "x": 34.98, "msl": 2.87 },
  { "x": 36.04, "msl": 2.98 },
  { "x": 37.10, "msl": 3.18 },
  { "x": 38.16, "msl": 3.43 },
  { "x": 39.22, "msl": 3.87 },
  { "x": 40.28, "msl": 4.68 },
  { "x": 41.34, "msl": 6.26 },
  { "x": 42.40, "msl": 7.11 },
  { "x": 43.46, "msl": 7.98 },
  { "x": 44.52, "msl": 9.14 },
  { "x": 45.58, "msl": 9.82 },
  { "x": 46.64, "msl": 9.80 },
  { "x": 46.64, "msl": 9.80 }
]
